ortei/__init__.py
ortei/_engine_evaluater_.py
ortei/_iort_engine_.py
ortei-0.1.1.dist-info/LICENSE
ortei-0.1.1.dist-info/METADATA
ortei-0.1.1.dist-info/WHEEL
ortei-0.1.1.dist-info/top_level.txt
ortei-0.1.1.dist-info/RECORD
