Metadata-Version: 2.1
Name: ortei
Version: 0.1.1
Summary: ONNX-Runtime-Engine-Interface
Home-page: https://github.com/404Vector/Package.ONNX-Runtime-Engine-Interface/tree/main
Author: 404Vector
Author-email: tiryul@gmail.com
Keywords: 404Vector,ortei
Classifier: Programming Language :: Python :: 3.8
Classifier: Programming Language :: Python :: 3.9
Classifier: Programming Language :: Python :: 3.10
Requires-Python: >=3.8
License-File: LICENSE
Requires-Dist: pandas
Requires-Dist: pytz
Requires-Dist: tqdm
